README.md
setup.py
leviathan/__init__.py
leviathan_profiler.egg-info/PKG-INFO
leviathan_profiler.egg-info/SOURCES.txt
leviathan_profiler.egg-info/dependency_links.txt
leviathan_profiler.egg-info/requires.txt
leviathan_profiler.egg-info/top_level.txt